Metadata-Version: 2.1
Name: smguseres
Version: 1.0.0
Summary: Python tool to generate UseResource files for Super Mario Galaxy 2 using Dolphin logs.
Home-page: https://github.com/SunakazeKun/pyjkernel
Author: Aurum
License: gpl-3.0
Keywords: nintendo,super-mario-galaxy,archive,modding
Platform: UNKNOWN
Classifier: Intended Audience :: Developers
Classifier: Topic :: Software Development :: Libraries
Classifier: License :: OSI Approved :: GNU General Public License v3 (GPLv3)
Classifier: Programming Language :: Python :: 3 :: Only
Requires-Python: >=3.6
